README.md
setup.py
ajelastic/__init__.py
ajelastic/definition.py
ajelastic/exceptions.py
ajelastic/index.py
ajelastic.egg-info/PKG-INFO
ajelastic.egg-info/SOURCES.txt
ajelastic.egg-info/dependency_links.txt
ajelastic.egg-info/entry_points.txt
ajelastic.egg-info/not-zip-safe
ajelastic.egg-info/top_level.txt
ajelastic/commands/__init__.py
ajelastic/commands/base.py
ajelastic/commands/reindex.py
ajelastic/conf/__init__.py
ajelastic/querybuilder/__init__.py
ajelastic/querybuilder/filters.py