Metadata-Version: 2.1
Name: ajelastic
Version: 1.0.1
Summary: Python - Elasticsearch Integration (for Aasaanjobs Internal Usage)
Home-page: https://github.com/aasaanjobs/ajelastic-sdk
Author: Sohel Tarir
Author-email: sohel.tarir@aasaanjobs.com
License: MIT
Platform: UNKNOWN
Classifier: Development Status :: 4 - Beta
Classifier: Environment :: Web Environment
Classifier: Intended Audience :: Developers
Classifier: License :: OSI Approved :: MIT License
Classifier: Operating System :: OS Independent
Classifier: Programming Language :: Python
Classifier: Programming Language :: Python :: 3.5
Classifier: Programming Language :: Python :: 3.6
